{
   "empirical": {
      "metadata": {},
      "gflops": {
         "data": [
            [
               "FP64 GFLOPs",
               4730.94
            ]
         ],
         "metadata": {
            "": [
               "META_DATA",
               "FLOPS          2",
               "MPI_PROCS      128",
               "ERT_VERSION  1.1.0",
               "HOSTNAME  ('tcn215.local.snellius.surf.nl', [], ['172.18.56.225'])",
               "UNAME  uname_result(system='Linux', node='tcn215.local.snellius.surf.nl', release='4.18.0-372.80.1.el8_6.x86_64', version='#1 SMP Fri Nov 3 14:30:16 EDT 2023', machine='x86_64', processor='x86_64')",
               "TIMESTAMP_DATA  1707390232.5364397",
               "CONFIG  {'ERT_RESULTS': ['Results.snellius.01'], 'ERT_DRIVER': ['driver1'], 'ERT_KERNEL': ['kernel1'], 'ERT_MPI': ['True'], 'ERT_MPI_CFLAGS': [], 'ERT_MPI_LDFLAGS': [], 'ERT_OPENMP': ['False'], 'ERT_OPENMP_CFLAGS': ['-fopenmp'], 'ERT_OPENMP_LDFLAGS': ['-fopenmp'], 'ERT_FLOPS': ['1,2,4,8'], 'ERT_ALIGN': ['32'], 'ERT_CC': ['mpic++'], 'ERT_CFLAGS': ['-Ofast', '-fargument-noalias', '-mavx2'], 'ERT_LD': ['mpic++'], 'ERT_LDFLAGS': [], 'ERT_LDLIBS': [], 'ERT_RUN': ['export', 'OMP_NUM_THREADS=ERT_OPENMP_THREADS;', 'mpirun', '-np', 'ERT_MPI_PROCS', 'ERT_CODE'], 'ERT_PROCS_THREADS': ['32,64,128'], 'ERT_MPI_PROCS': ['32,64,128'], 'ERT_OPENMP_THREADS': [], 'ERT_NUM_EXPERIMENTS': ['5'], 'ERT_MEMORY_MAX': ['1357905920'], 'ERT_WORKING_SET_MIN': ['1'], 'ERT_TRIALS_MIN': ['1'], 'ERT_GNUPLOT': ['gnuplot'], 'ERT_GPU': [False], 'ERT_HIP': [False], 'ERT_PRECISION': ['FP64'], 'ERT_OCL': [False], 'ERT_SYCL': [False], 'ERT_WSS_MULT': [1.1]}",
               "TIMESTAMP_DATA  1707390259.3931015",
               "TIMESTAMP_DATA  1707390286.6887612",
               "TIMESTAMP_DATA  1707390313.2180014",
               "TIMESTAMP_DATA  1707390339.9720724"
            ],
            "TIMESTAMP_DB": 1707390902.7745001
         }
      },
      "gbytes": {
         "data": [
            [
               "L1",
               37972.32
            ],
            [
               "L2",
               31473.72
            ],
            [
               "L3",
               5243.76
            ],
            [
               "DRAM",
               285.9
            ]
         ],
         "metadata": {
            "": [
               "FLOPS          1",
               "MPI_PROCS      128",
               "ERT_VERSION  1.1.0",
               "HOSTNAME  ('tcn215.local.snellius.surf.nl', [], ['172.18.56.225'])",
               "UNAME  uname_result(system='Linux', node='tcn215.local.snellius.surf.nl', release='4.18.0-372.80.1.el8_6.x86_64', version='#1 SMP Fri Nov 3 14:30:16 EDT 2023', machine='x86_64', processor='x86_64')",
               "TIMESTAMP_DATA  1707389966.8165777",
               "CONFIG  {'ERT_RESULTS': ['Results.snellius.01'], 'ERT_DRIVER': ['driver1'], 'ERT_KERNEL': ['kernel1'], 'ERT_MPI': ['True'], 'ERT_MPI_CFLAGS': [], 'ERT_MPI_LDFLAGS': [], 'ERT_OPENMP': ['False'], 'ERT_OPENMP_CFLAGS': ['-fopenmp'], 'ERT_OPENMP_LDFLAGS': ['-fopenmp'], 'ERT_FLOPS': ['1,2,4,8'], 'ERT_ALIGN': ['32'], 'ERT_CC': ['mpic++'], 'ERT_CFLAGS': ['-Ofast', '-fargument-noalias', '-mavx2'], 'ERT_LD': ['mpic++'], 'ERT_LDFLAGS': [], 'ERT_LDLIBS': [], 'ERT_RUN': ['export', 'OMP_NUM_THREADS=ERT_OPENMP_THREADS;', 'mpirun', '-np', 'ERT_MPI_PROCS', 'ERT_CODE'], 'ERT_PROCS_THREADS': ['32,64,128'], 'ERT_MPI_PROCS': ['32,64,128'], 'ERT_OPENMP_THREADS': [], 'ERT_NUM_EXPERIMENTS': ['5'], 'ERT_MEMORY_MAX': ['1357905920'], 'ERT_WORKING_SET_MIN': ['1'], 'ERT_TRIALS_MIN': ['1'], 'ERT_GNUPLOT': ['gnuplot'], 'ERT_GPU': [False], 'ERT_HIP': [False], 'ERT_PRECISION': ['FP64'], 'ERT_OCL': [False], 'ERT_SYCL': [False], 'ERT_WSS_MULT': [1.1]}",
               "TIMESTAMP_DATA  1707389993.7727787",
               "TIMESTAMP_DATA  1707390021.005387",
               "TIMESTAMP_DATA  1707390048.3875697",
               "TIMESTAMP_DATA  1707390076.1311302"
            ],
            "TIMESTAMP_DB": 1707390902.7745812
         }
      }
   },
   "spec": {
      "gflops": {
         "data": []
      },
      "gbytes": {
         "data": []
      }
   }
}